main.py
pypi_package_example_bunyaminergen-0.1.dist-info/LICENSE
pypi_package_example_bunyaminergen-0.1.dist-info/METADATA
pypi_package_example_bunyaminergen-0.1.dist-info/WHEEL
pypi_package_example_bunyaminergen-0.1.dist-info/top_level.txt
pypi_package_example_bunyaminergen-0.1.dist-info/RECORD
