Metadata-Version: 2.1
Name: pypi-package-example-bunyaminergen
Version: 0.1
Summary: trying pypi_package_example 
Home-page: 
Author: BE
Author-email: bunyaminergen@yahoo.com.tr
License: ISO
License-File: LICENSE
